protlearn/__init__.py
protlearn/dimreduction/__init__.py
protlearn/dimreduction/correlation.py
protlearn/dimreduction/lasso.py
protlearn/dimreduction/lda.py
protlearn/dimreduction/pca.py
protlearn/dimreduction/rfe.py
protlearn/dimreduction/sequential.py
protlearn/dimreduction/tree_importance.py
protlearn/dimreduction/tsne.py
protlearn/dimreduction/univariate_filter.py
protlearn/dimreduction/tests/__init__.py
protlearn/dimreduction/tests/test_correlation.py
protlearn/dimreduction/tests/test_lasso.py
protlearn/dimreduction/tests/test_lda.py
protlearn/dimreduction/tests/test_pca.py
protlearn/dimreduction/tests/test_rfe.py
protlearn/dimreduction/tests/test_sequential.py
protlearn/dimreduction/tests/test_tree_importance.py
protlearn/dimreduction/tests/test_tsne.py
protlearn/dimreduction/tests/test_univariate_filter.py
protlearn/features/__init__.py
protlearn/features/aac.py
protlearn/features/aaindex1.py
protlearn/features/apaac.py
protlearn/features/atc.py
protlearn/features/binary.py
protlearn/features/cksaap.py
protlearn/features/ctd.py
protlearn/features/ctdc.py
protlearn/features/ctdd.py
protlearn/features/ctdt.py
protlearn/features/entropy.py
protlearn/features/geary.py
protlearn/features/length.py
protlearn/features/moran.py
protlearn/features/moreau_broto.py
protlearn/features/motif.py
protlearn/features/ngram.py
protlearn/features/paac.py
protlearn/features/posrich.py
protlearn/features/qso.py
protlearn/features/socn.py
protlearn/features/data/aaindex1.csv
protlearn/features/data/atc.csv
protlearn/features/data/ctd.csv
protlearn/features/data/grantham.csv
protlearn/features/data/paac.csv
protlearn/features/data/schneider-wrede.csv
protlearn/features/tests/__init__.py
protlearn/features/tests/test_aac.py
protlearn/features/tests/test_aaindex1.py
protlearn/features/tests/test_apaac.py
protlearn/features/tests/test_atc.py
protlearn/features/tests/test_binary.py
protlearn/features/tests/test_cksaap.py
protlearn/features/tests/test_ctd.py
protlearn-0.0.3.dist-info/LICENSE
protlearn-0.0.3.dist-info/METADATA
protlearn-0.0.3.dist-info/WHEEL
protlearn-0.0.3.dist-info/top_level.txt
protlearn-0.0.3.dist-info/RECORD
