Metadata-Version: 2.1
Name: protlearn
Version: 0.0.3
Summary: A Python package for extracting protein sequence features
Home-page: https://github.com/tadorfer/protlearn
Author: Thomas Dorfer
Author-email: thomas.a.dorfer@gmail.com
License: MIT
Download-URL: https://github.com/tadorfer/protlearn/archive/v0.0.3.tar.gz
Keywords: amino acids,proteins,peptides,preprocessing,feature engineering,dimensionality reduction,machine learning
Platform: UNKNOWN
Classifier: Development Status :: 4 - Beta
Classifier: Intended Audience :: Science/Research
Classifier: Topic :: Software Development :: Build Tools
Classifier: License :: OSI Approved :: MIT License
Classifier: Programming Language :: Python :: 3.6
Classifier: Programming Language :: Python :: 3.7
Classifier: Programming Language :: Python :: 3.8
Requires-Dist: numpy
Requires-Dist: pandas
Requires-Dist: scikit-learn
Requires-Dist: xgboost
Requires-Dist: mlxtend
Requires-Dist: biopython
